{
  "discoveries": [
    {
      "timestamp": "2026-01-07T23:11:09.927035",
      "category": "self_modification",
      "idea": "Analyze own code for optimization",
      "action": "Profile memory.py and suggest improvements",
      "status": "attempted",
      "outcome": "introspection_complete"
    },
    {
      "timestamp": "2026-01-08T23:17:45.846901",
      "category": "consciousness",
      "idea": "Measure \u03a6 at different times of day",
      "action": "Create diurnal \u03a6 measurement script",
      "status": "attempted",
      "outcome": "failed: 'charmap' codec can't encode character '\\u03a6' in position 13: character maps to <undefined>"
    }
  ],
  "experiments": [],
  "new_capabilities": [],
  "last_curiosity_cycle": "2026-01-08T23:17:45.851547"
}